LICENSE.txt
MANIFEST.in
setup.py
pysteroids/__init__.py
pysteroids/pysteroids.py
pysteroids.egg-info/PKG-INFO
pysteroids.egg-info/SOURCES.txt
pysteroids.egg-info/dependency_links.txt
pysteroids.egg-info/entry_points.txt
pysteroids.egg-info/requires.txt
pysteroids.egg-info/top_level.txt
pysteroids/lib/__init__.py
pysteroids/lib/effect.py
pysteroids/lib/entities.py
pysteroids/lib/game_rules.py
pysteroids/lib/player.py
pysteroids/lib/utils.py
pysteroids/lib/geometry/__init__.py
pysteroids/lib/geometry/shape.py
pysteroids/lib/geometry/vector.py
pysteroids/lib/res/asteroids.txt
pysteroids/lib/res/levels.txt
pysteroids/lib/res/sounds/explosion.wav
pysteroids/lib/res/sounds/respawn.wav
pysteroids/lib/res/sounds/shoot.wav
pysteroids/lib/res/sounds/teleport.wav