Metadata-Version: 1.1
Name: pysteroids
Version: 1.0.1
Summary: A clone of the game Asteroids, with some extra bells and whistles
Home-page: https://github.com/Cheeser12/pysteroids
Author: Max Mays
Author-email: wmays@max-mays.com
License: MIT
Keywords: game asteroids
Platform: UNKNOWN
Classifier: License :: OSI Approved :: MIT License
Classifier: Operating System :: OS Independent
Classifier: Topic :: Games/Entertainment
Classifier: Topic :: Games/Entertainment :: Arcade
Classifier: Programming Language :: Python :: 2.7
